common/common.py
common/log_time.py
converter/__init__.py
converter/board_ref.py
converter/fen.py
converter/headers.py
converter/pgn_data.py
converter/process.py
converter/result.py
testing/test.py
pgn2data-0.0.9.dist-info/LICENSE
pgn2data-0.0.9.dist-info/METADATA
pgn2data-0.0.9.dist-info/WHEEL
pgn2data-0.0.9.dist-info/top_level.txt
pgn2data-0.0.9.dist-info/RECORD
