Metadata-Version: 2.1
Name: pgn2data
Version: 0.0.9
Summary: Converts a chess pgn file into a csv dataset containing game information and move information
Home-page: https://github.com/zq99/pgn2data
Author: zq99
Author-email: zq99@hotmail.com
License: GPL-3.0+
Keywords: CHESS,PGN,NOTATION,DATA,FORSYTH–EDWARDS NOTATION,CSV,DATASET,DATABASE,NORMALIZATION,TABULATION,STRUCTURED DATA,SQL,TABLE,EXCEL,PYTHON-CHESS
Classifier: Development Status :: 5 - Production/Stable
Classifier: Intended Audience :: Education
Classifier: Operating System :: Microsoft :: Windows :: Windows 10
Classifier: License :: OSI Approved :: GNU General Public License v3 or later (GPLv3+)
Classifier: Programming Language :: Python :: 3 :: Only
Classifier: Programming Language :: Python :: 3.7
Classifier: Programming Language :: Python :: 3.8
Classifier: Programming Language :: Python :: 3.9
Classifier: Programming Language :: Python :: 3.10
Requires-Python: >=3.7
License-File: LICENSE
Requires-Dist: chess
Requires-Dist: pandas
